Metadata-Version: 1.1
Name: numerov
Version: 0.5.0
Summary: Compute vibrational levels, wavefunctions, and expectation values using the Numerov-Cooley algorithm.
Home-page: https://github.com/bast/numerov
Author: Radovan Bast
Author-email: radovan.bast@uit.no
License: MPL-2.0
Platform: UNKNOWN
Classifier: Development Status :: 3 - Alpha
Classifier: Intended Audience :: Science/Research
Classifier: Programming Language :: Python :: 2.7
Classifier: Programming Language :: Python :: 3.6
